{
  "id": "http://w3id.org/openeduhub/vocabs/eaf-schlagwortverzeichnis-all/FC7032F3B1DBAD31C1256F230035BBC9",
  "type": "Concept",
  "followers": "https://test.skohub.io/followers?subject=w3id.org%2Fopeneduhub%2Fvocabs%2Feaf-schlagwortverzeichnis-all%2FFC7032F3B1DBAD31C1256F230035BBC9",
  "inbox": "https://test.skohub.io/inbox?target=w3id.org%2Fopeneduhub%2Fvocabs%2Feaf-schlagwortverzeichnis-all%2FFC7032F3B1DBAD31C1256F230035BBC9",
  "prefLabel": {
    "de": "Kraft"
  },
  "narrower": [
    {
      "id": "http://w3id.org/openeduhub/vocabs/eaf-schlagwortverzeichnis-all/0B8E544DE94CC492C1256F2300360BD9",
      "prefLabel": {
        "de": "Wirkung (Physik)"
      }
    },
    {
      "id": "http://w3id.org/openeduhub/vocabs/eaf-schlagwortverzeichnis-all/0FB7B9F7DB02D593C1257A80004D0C22",
      "prefLabel": {
        "de": "Aktionsgesetz"
      }
    },
    {
      "id": "http://w3id.org/openeduhub/vocabs/eaf-schlagwortverzeichnis-all/48C3B9252EEED642C1257CE8002C0F17",
      "prefLabel": {
        "de": "feste Rolle"
      }
    },
    {
      "id": "http://w3id.org/openeduhub/vocabs/eaf-schlagwortverzeichnis-all/4EB91B013823A520C125730200335D69",
      "prefLabel": {
        "de": "Anziehung"
      }
    },
    {
      "id": "http://w3id.org/openeduhub/vocabs/eaf-schlagwortverzeichnis-all/93F57BCF28144D47C12578BB00345865",
      "prefLabel": {
        "de": "Rolle (Physik)"
      }
    },
    {
      "id": "http://w3id.org/openeduhub/vocabs/eaf-schlagwortverzeichnis-all/A32CFE53FCA4B9DFC1257F460058431C",
      "prefLabel": {
        "de": "Kräftegleichgewicht"
      }
    },
    {
      "id": "http://w3id.org/openeduhub/vocabs/eaf-schlagwortverzeichnis-all/D26790743490E105C125756C0037A1D9",
      "prefLabel": {
        "de": "Mechanik"
      }
    }
  ],
  "broader": {
    "id": "http://w3id.org/openeduhub/vocabs/eaf-schlagwortverzeichnis-all/physik",
    "prefLabel": {
      "de": "Physik"
    }
  },
  "inScheme": {
    "id": "http://w3id.org/openeduhub/vocabs/eaf-schlagwortverzeichnis-all/",
    "title": {
      "de": "eaf-schlagwortverzeichnis-all"
    }
  },
  "@context": {
    "@version": 1.1,
    "id": "@id",
    "type": "@type",
    "@vocab": "http://www.w3.org/2004/02/skos/core#",
    "xsd": "http://www.w3.org/2001/XMLSchema#",
    "dct": "http://purl.org/dc/terms/",
    "schema": "http://schema.org/",
    "vann": "http://purl.org/vocab/vann/",
    "as": "https://www.w3.org/ns/activitystreams#",
    "ldp": "http://www.w3.org/ns/ldp#",
    "title": {
      "@id": "dct:title",
      "@container": "@language"
    },
    "description": {
      "@id": "dct:description",
      "@container": "@language"
    },
    "issued": {
      "@id": "dct:issued",
      "@type": "xsd:date"
    },
    "created": {
      "@id": "dct:created",
      "@type": "xsd:date"
    },
    "modified": {
      "@id": "dct:modified",
      "@type": "xsd:date"
    },
    "creator": "dct:creator",
    "publisher": "dct:publisher",
    "preferredNamespacePrefix": "vann:preferredNamespacePrefix",
    "preferredNamespaceUri": "vann:preferredNamespaceUri",
    "isBasedOn": "schema:isBasedOn",
    "source": "dct:source",
    "prefLabel": {
      "@container": "@language"
    },
    "hiddenLabel": {
      "@container": [
        "@language",
        "@set"
      ]
    },
    "altLabel": {
      "@container": [
        "@language",
        "@set"
      ]
    },
    "definition": {
      "@container": "@language"
    },
    "scopeNote": {
      "@container": [
        "@language",
        "@set"
      ]
    },
    "note": {
      "@container": [
        "@language",
        "@set"
      ]
    },
    "notation": {
      "@container": "@set"
    },
    "narrower": {
      "@container": "@set"
    },
    "narrowerTransitive": {
      "@container": "@set"
    },
    "broaderTransitive": {
      "@container": "@set"
    },
    "followers": "as:followers",
    "inbox": "ldp:inbox"
  }
}